__init__.py
gnornir_utils.py
gsshuttle.py
gautilus-0.0.3.dist-info/LICENSE
gautilus-0.0.3.dist-info/METADATA
gautilus-0.0.3.dist-info/WHEEL
gautilus-0.0.3.dist-info/top_level.txt
gautilus-0.0.3.dist-info/RECORD
