Metadata-Version: 2.1
Name: gautilus
Version: 0.0.3
Summary: G automation utils
Author-email: garrettl <galanger99@gmail.com>
License: MIT License        
Classifier: Programming Language :: Python :: 3
Classifier: License :: OSI Approved :: MIT License
Classifier: Operating System :: OS Independent
Requires-Python: >=3.7
License-File: LICENSE
Requires-Dist: nornir
Requires-Dist: boto3
Requires-Dist: pandas
Requires-Dist: importlib-metadata ; python_version < "3.8"
